bili_video_converter/__init__.py
bili_video_converter/bili_convert.py
bili_video_converter-0.1.2.dist-info/METADATA
bili_video_converter-0.1.2.dist-info/WHEEL
bili_video_converter-0.1.2.dist-info/entry_points.txt
bili_video_converter-0.1.2.dist-info/licenses/LICENSE
bili_video_converter-0.1.2.dist-info/RECORD
